{
  "individualResults": [
    {
      "initialSchemaVersion": "3",
      "targetSchemaVersion": null,
      "schemaName": "",
      "migrations": [],
      "migrationsExecuted": 0,
      "success": true,
      "flywayVersion": "9.22.2",
      "database": "u440037415_dev_depgirpro",
      "warnings": [],
      "timestamp": "2023-10-12T22:28:27.052585",
      "operation": "migrate",
      "exception": null,
      "licenseFailed": false
    },
    {
      "schemaVersion": "3",
      "schemaName": "",
      "migrations": [
        {
          "category": "Versioned",
          "version": "1",
          "rawVersion": "1",
          "description": "create-table-eventos",
          "type": "SQL",
          "installedOnUTC": "2023-10-10T10:38:52Z",
          "state": "Future",
          "undoable": "No",
          "filepath": "",
          "undoFilepath": "",
          "installedBy": "u440037415_dev_depgirpro",
          "executionTime": 336
        },
        {
          "category": "Versioned",
          "version": "2",
          "rawVersion": "2",
          "description": "create-table-usuarios",
          "type": "SQL",
          "installedOnUTC": "2023-10-10T10:38:54Z",
          "state": "Future",
          "undoable": "No",
          "filepath": "",
          "undoFilepath": "",
          "installedBy": "u440037415_dev_depgirpro",
          "executionTime": 344
        },
        {
          "category": "Versioned",
          "version": "3",
          "rawVersion": "3",
          "description": "create-table-asistentes",
          "type": "SQL",
          "installedOnUTC": "2023-10-10T10:38:57Z",
          "state": "Future",
          "undoable": "No",
          "filepath": "",
          "undoFilepath": "",
          "installedBy": "u440037415_dev_depgirpro",
          "executionTime": 535
        }
      ],
      "flywayVersion": "9.22.2",
      "database": "u440037415_dev_depgirpro",
      "allSchemasEmpty": false,
      "timestamp": "2023-10-12T22:29:29.772696400",
      "operation": "info",
      "exception": null,
      "licenseFailed": false
    },
    {
      "initialSchemaVersion": null,
      "targetSchemaVersion": "1",
      "schemaName": "",
      "migrations": [
        {
          "category": "Versioned",
          "version": "1",
          "description": "Tabla jugadores",
          "type": "SQL",
          "filepath": "C:\\Users\\javie\\OneDrive\\Escritorio\\DB-Girarpro2\\db-depgirpro\\BD_Tablas\\V1__Tabla_jugadores.sql",
          "executionTime": 463
        }
      ],
      "migrationsExecuted": 1,
      "success": true,
      "flywayVersion": "9.22.2",
      "database": "u440037415_dev_depgirpro",
      "warnings": [],
      "timestamp": "2023-10-13T21:29:16.720574900",
      "operation": "migrate",
      "exception": null,
      "licenseFailed": false
    },
    {
      "initialSchemaVersion": null,
      "targetSchemaVersion": null,
      "schemaName": "",
      "migrations": [],
      "migrationsExecuted": 0,
      "success": true,
      "flywayVersion": "9.22.2",
      "database": "u440037415_dev_depgirpro",
      "warnings": [],
      "timestamp": "2023-10-17T21:10:57.301594400",
      "operation": "migrate",
      "exception": null,
      "licenseFailed": false
    },
    {
      "initialSchemaVersion": null,
      "targetSchemaVersion": null,
      "schemaName": "",
      "migrations": [],
      "migrationsExecuted": 0,
      "success": true,
      "flywayVersion": "9.22.2",
      "database": "u440037415_dev_depgirpro",
      "warnings": [],
      "timestamp": "2023-10-17T21:14:19.172388600",
      "operation": "migrate",
      "exception": null,
      "licenseFailed": false
    },
    {
      "initialSchemaVersion": null,
      "targetSchemaVersion": null,
      "schemaName": "",
      "migrations": [],
      "migrationsExecuted": 0,
      "success": true,
      "flywayVersion": "9.22.2",
      "database": "u440037415_dev_depgirpro",
      "warnings": [],
      "timestamp": "2023-10-17T21:17:14.076351400",
      "operation": "migrate",
      "exception": null,
      "licenseFailed": false
    },
    {
      "initialSchemaVersion": null,
      "targetSchemaVersion": null,
      "schemaName": "",
      "migrations": [],
      "migrationsExecuted": 0,
      "success": true,
      "flywayVersion": "9.22.2",
      "database": "u440037415_dev_depgirpro",
      "warnings": [],
      "timestamp": "2023-10-17T21:18:18.429840700",
      "operation": "migrate",
      "exception": null,
      "licenseFailed": false
    },
    {
      "initialSchemaVersion": null,
      "targetSchemaVersion": null,
      "schemaName": "",
      "migrations": [],
      "migrationsExecuted": 0,
      "success": true,
      "flywayVersion": "9.22.2",
      "database": "u440037415_dev_depgirpro",
      "warnings": [],
      "timestamp": "2023-10-17T21:19:23.204765300",
      "operation": "migrate",
      "exception": null,
      "licenseFailed": false
    },
    {
      "initialSchemaVersion": null,
      "targetSchemaVersion": null,
      "schemaName": "",
      "migrations": [],
      "migrationsExecuted": 0,
      "success": true,
      "flywayVersion": "9.22.2",
      "database": "u440037415_dev_depgirpro",
      "warnings": [],
      "timestamp": "2023-10-17T21:21:55.051505400",
      "operation": "migrate",
      "exception": null,
      "licenseFailed": false
    }
  ]
}